wikilangs/__init__.py
wikilangs/embeddings.py
wikilangs/languages.py
wikilangs/llm.py
wikilangs/markov.py
wikilangs/ngram.py
wikilangs/tokenizer.py
wikilangs/vocabulary.py
wikilangs-0.1.2.dist-info/METADATA
wikilangs-0.1.2.dist-info/WHEEL
wikilangs-0.1.2.dist-info/top_level.txt
wikilangs-0.1.2.dist-info/RECORD
