Metadata-Version: 2.4
Name: wikilangs
Version: 0.1.2
Summary: A Python package for consuming Wikipedia language models including tokenizers, ngram models, markov chains, and vocabularies.
Author-email: Omar Kamali <wikilangs@omarkama.li>
License: MIT
Project-URL: Homepage, https://github.com/wikilangs/wikilangs
Project-URL: Repository, https://github.com/wikilangs/wikilangs.git
Project-URL: Bug Tracker, https://github.com/wikilangs/wikilangs/issues
Classifier: Development Status :: 3 - Alpha
Classifier: Intended Audience :: Developers
Classifier: Intended Audience :: Science/Research
Classifier: License :: OSI Approved :: MIT License
Classifier: Programming Language :: Python :: 3
Classifier: Programming Language :: Python :: 3.11
Classifier: Programming Language :: Python :: 3.12
Classifier: Programming Language :: Python :: 3.13
Classifier: Programming Language :: Python :: 3.14
Classifier: Topic :: Scientific/Engineering :: Artificial Intelligence
Classifier: Topic :: Text Processing :: Linguistic
Requires-Python: >=3.11
Requires-Dist: pandas==2.3.3
Requires-Dist: pyarrow==22.0.0
Requires-Dist: huggingface_hub==0.36.0
Requires-Dist: datasets==4.4.2
Requires-Dist: pycountry==24.6.1
Requires-Dist: vocabulous==0.1.3
Requires-Dist: tokenizers==0.22.1
Requires-Dist: transformers==4.57.3
Requires-Dist: sentencepiece==0.2.1
Requires-Dist: torch==2.9.1
Requires-Dist: numpy==2.2.3
Requires-Dist: babelvec==0.1.5
Provides-Extra: test
Requires-Dist: pytest>=7.0; extra == "test"
Requires-Dist: pytest-cov>=4.0; extra == "test"
Provides-Extra: examples
Requires-Dist: jupyter>=1.0.0; extra == "examples"
